{"id":84721,"title":"[The syndrome of chronic inflammation of adipose tissue].","abstract":"The pathogenetic role of adipose tissue chronic inflammation syndrome in development of atherosclerosis, type II diabetes, metabolic syndrome and hypertension is being discussed.","date":"2014-07-23","categories":"Pathological Conditions and Signs and Symptoms","split":"train","url":"http://www.ncbi.nlm.nih.gov/pubmed/25051689","annotations":[{"name":"Metabolic syndrome","weight":0.889807,"wikipedia_article":"http://en.wikipedia.org/wiki/Metabolic_syndrome"},{"name":"Atherosclerosis","weight":0.889548,"wikipedia_article":"http://en.wikipedia.org/wiki/Atherosclerosis"},{"name":"Adipose tissue","weight":0.834954,"wikipedia_article":"http://en.wikipedia.org/wiki/Adipose_tissue"},{"name":"Diabetes mellitus","weight":0.834159,"wikipedia_article":"http://en.wikipedia.org/wiki/Diabetes_mellitus"},{"name":"Hypertension","weight":0.820237,"wikipedia_article":"http://en.wikipedia.org/wiki/Hypertension"},{"name":"Diabetes mellitus type 2","weight":0.812569,"wikipedia_article":"http://en.wikipedia.org/wiki/Diabetes_mellitus_type_2"},{"name":"Inflammation","weight":0.791078,"wikipedia_article":"http://en.wikipedia.org/wiki/Inflammation"},{"name":"Metabolism","weight":0.71741,"wikipedia_article":"http://en.wikipedia.org/wiki/Metabolism"},{"name":"Tissue (biology)","weight":0.585738,"wikipedia_article":"http://en.wikipedia.org/wiki/Tissue_(biology)"},{"name":"Chronic (medicine)","weight":0.585738,"wikipedia_article":"http://en.wikipedia.org/wiki/Chronic_(medicine)"},{"name":"Syndrome","weight":0.573549,"wikipedia_article":"http://en.wikipedia.org/wiki/Syndrome"},{"name":"Pathogenesis","weight":0.37066,"wikipedia_article":"http://en.wikipedia.org/wiki/Pathogenesis"},{"name":"Chronic inflammation","weight":0.251754,"wikipedia_article":"http://en.wikipedia.org/wiki/Chronic_inflammation"},{"name":"Developmental biology","weight":0.0298055,"wikipedia_article":"http://en.wikipedia.org/wiki/Developmental_biology"},{"name":"Nuclear receptor","weight":0.0168623,"wikipedia_article":"http://en.wikipedia.org/wiki/Nuclear_receptor"},{"name":"Type (biology)","weight":0.0147415,"wikipedia_article":"http://en.wikipedia.org/wiki/Type_(biology)"}]}
